justplotme/__init__.py
justplotme/llm.py
justplotme/static/widget.css
justplotme/static/widget.js
justplotme-0.0.1.dist-info/METADATA
justplotme-0.0.1.dist-info/WHEEL
justplotme-0.0.1.dist-info/licenses/LICENSE
justplotme-0.0.1.dist-info/RECORD
