Metadata-Version: 2.3
Name: justplotme
Version: 0.0.1
Author-email: nuwandavek <vivekaithal44@gmail.com>
License-File: LICENSE
Requires-Dist: anywidget
Requires-Dist: bs4
Requires-Dist: markdown
Requires-Dist: openai
Requires-Dist: pandas
Requires-Dist: plotly
Provides-Extra: dev
Requires-Dist: jupyterlab; extra == 'dev'
Requires-Dist: watchfiles; extra == 'dev'
